[
    {
        "id": 12001001,
        "templateId": 1,
        "starLevel": 1,
        "describe": "\u4e0a\u5b98\u7fce",
        "attack": 0,
        "defence": 0,
        "health": 0,
        "magic": 0,
        "attackSpeed": 0,
        "moveSpeed": 0,
        "attackRange": 0
    },
    {
        "id": 12001002,
        "templateId": 1,
        "starLevel": 2,
        "describe": "\u4e0a\u5b98\u7fce",
        "attack": 10,
        "defence": 2,
        "health": 50,
        "magic": 20,
        "attackSpeed": 50,
        "moveSpeed": 500,
        "attackRange": 0
    },
    {
        "id": 12001003,
        "templateId": 1,
        "starLevel": 3,
        "describe": "\u4e0a\u5b98\u7fce",
        "attack": 11,
        "defence": 3,
        "health": 51,
        "magic": 21,
        "attackSpeed": 51,
        "moveSpeed": 501,
        "attackRange": 0
    },
    {
        "id": 12001004,
        "templateId": 1,
        "starLevel": 4,
        "describe": "\u4e0a\u5b98\u7fce",
        "attack": 12,
        "defence": 4,
        "health": 52,
        "magic": 22,
        "attackSpeed": 52,
        "moveSpeed": 502,
        "attackRange": 0
    },
    {
        "id": 12001005,
        "templateId": 1,
        "starLevel": 5,
        "describe": "\u4e0a\u5b98\u7fce",
        "attack": 13,
        "defence": 5,
        "health": 53,
        "magic": 23,
        "attackSpeed": 53,
        "moveSpeed": 503,
        "attackRange": 0
    },
    {
        "id": 12001006,
        "templateId": 1,
        "starLevel": 6,
        "describe": "\u4e0a\u5b98\u7fce",
        "attack": 14,
        "defence": 6,
        "health": 54,
        "magic": 24,
        "attackSpeed": 54,
        "moveSpeed": 504,
        "attackRange": 0
    },
    {
        "id": 12001007,
        "templateId": 1,
        "starLevel": 7,
        "describe": "\u4e0a\u5b98\u7fce",
        "attack": 15,
        "defence": 7,
        "health": 55,
        "magic": 25,
        "attackSpeed": 55,
        "moveSpeed": 505,
        "attackRange": 0
    },
    {
        "id": 12001008,
        "templateId": 1,
        "starLevel": 8,
        "describe": "\u4e0a\u5b98\u7fce",
        "attack": 16,
        "defence": 8,
        "health": 56,
        "magic": 26,
        "attackSpeed": 56,
        "moveSpeed": 506,
        "attackRange": 0
    },
    {
        "id": 12001009,
        "templateId": 1,
        "starLevel": 9,
        "describe": "\u4e0a\u5b98\u7fce",
        "attack": 17,
        "defence": 9,
        "health": 57,
        "magic": 27,
        "attackSpeed": 57,
        "moveSpeed": 507,
        "attackRange": 0
    },
    {
        "id": 12001010,
        "templateId": 1,
        "starLevel": 10,
        "describe": "\u4e0a\u5b98\u7fce",
        "attack": 18,
        "defence": 10,
        "health": 58,
        "magic": 28,
        "attackSpeed": 58,
        "moveSpeed": 508,
        "attackRange": 0
    },
    {
        "id": 12002001,
        "templateId": 2,
        "starLevel": 1,
        "describe": "\u51e4\u7d2b\u5915",
        "attack": 0,
        "defence": 0,
        "health": 0,
        "magic": 0,
        "attackSpeed": 0,
        "moveSpeed": 0,
        "attackRange": 0
    },
    {
        "id": 12002002,
        "templateId": 2,
        "starLevel": 2,
        "describe": "\u51e4\u7d2b\u5915",
        "attack": 151,
        "defence": 11,
        "health": 366,
        "magic": 226,
        "attackSpeed": 50,
        "moveSpeed": 500,
        "attackRange": 0
    },
    {
        "id": 12002003,
        "templateId": 2,
        "starLevel": 3,
        "describe": "\u51e4\u7d2b\u5915",
        "attack": 152,
        "defence": 12,
        "health": 367,
        "magic": 227,
        "attackSpeed": 51,
        "moveSpeed": 501,
        "attackRange": 0
    },
    {
        "id": 12002004,
        "templateId": 2,
        "starLevel": 4,
        "describe": "\u51e4\u7d2b\u5915",
        "attack": 153,
        "defence": 13,
        "health": 368,
        "magic": 228,
        "attackSpeed": 52,
        "moveSpeed": 502,
        "attackRange": 0
    },
    {
        "id": 12002005,
        "templateId": 2,
        "starLevel": 5,
        "describe": "\u51e4\u7d2b\u5915",
        "attack": 154,
        "defence": 14,
        "health": 369,
        "magic": 229,
        "attackSpeed": 53,
        "moveSpeed": 503,
        "attackRange": 0
    },
    {
        "id": 12002006,
        "templateId": 2,
        "starLevel": 6,
        "describe": "\u51e4\u7d2b\u5915",
        "attack": 155,
        "defence": 15,
        "health": 370,
        "magic": 230,
        "attackSpeed": 54,
        "moveSpeed": 504,
        "attackRange": 0
    },
    {
        "id": 12002007,
        "templateId": 2,
        "starLevel": 7,
        "describe": "\u51e4\u7d2b\u5915",
        "attack": 156,
        "defence": 16,
        "health": 371,
        "magic": 231,
        "attackSpeed": 55,
        "moveSpeed": 505,
        "attackRange": 0
    },
    {
        "id": 12002008,
        "templateId": 2,
        "starLevel": 8,
        "describe": "\u51e4\u7d2b\u5915",
        "attack": 157,
        "defence": 17,
        "health": 372,
        "magic": 232,
        "attackSpeed": 56,
        "moveSpeed": 506,
        "attackRange": 0
    },
    {
        "id": 12002009,
        "templateId": 2,
        "starLevel": 9,
        "describe": "\u51e4\u7d2b\u5915",
        "attack": 158,
        "defence": 18,
        "health": 373,
        "magic": 233,
        "attackSpeed": 57,
        "moveSpeed": 507,
        "attackRange": 0
    },
    {
        "id": 12002010,
        "templateId": 2,
        "starLevel": 10,
        "describe": "\u51e4\u7d2b\u5915",
        "attack": 159,
        "defence": 19,
        "health": 374,
        "magic": 234,
        "attackSpeed": 58,
        "moveSpeed": 508,
        "attackRange": 0
    }
]